liveproxy/__init__.py
liveproxy/argparser.py
liveproxy/files.py
liveproxy/main.py
liveproxy/server.py
liveproxy-2.0.0.dist-info/METADATA
liveproxy-2.0.0.dist-info/WHEEL
liveproxy-2.0.0.dist-info/entry_points.txt
liveproxy-2.0.0.dist-info/top_level.txt
liveproxy-2.0.0.dist-info/RECORD
