Metadata-Version: 2.1
Name: liveproxy
Version: 2.0.0
Summary: LiveProxy can redirect Livestreams to your favorite player on a lot of devices.
Home-page: https://github.com/back-to/liveproxy
Author: back-to
Author-email: backto@protonmail.ch
License: UNKNOWN
Project-URL: Source, https://github.com/back-to/liveproxy/
Project-URL: Tracker, https://github.com/back-to/liveproxy/issues
Keywords: LiveProxy Streamlink Youtube-DL
Platform: UNKNOWN
Classifier: Development Status :: 4 - Beta
Classifier: Environment :: Console
Classifier: Intended Audience :: End Users/Desktop
Classifier: Natural Language :: English
Classifier: Operating System :: MacOS
Classifier: Operating System :: Microsoft :: Windows
Classifier: Operating System :: POSIX
Classifier: Operating System :: Unix
Classifier: Programming Language :: Python :: 3.6
Classifier: Programming Language :: Python :: 3.7
Classifier: Programming Language :: Python :: 3.8
Classifier: Programming Language :: Python :: 3.9
Classifier: Programming Language :: Python
Classifier: Topic :: Internet :: WWW/HTTP
Classifier: Topic :: Multimedia :: Video
Classifier: Topic :: Utilities
Requires-Python: >=3.6, <4
